{
  "1": {
    "id": 1,
    "name": "Heavy Attack",
    "description": "Moves triggered by holding down the Basic Attack button",
    "tag_type": 2,
    "parent_tag": 1001
  },
  "2": {
    "id": 2,
    "name": "Plunge Attack",
    "description": "Falling moves executed by using Basic Attacks from a certain height above the ground",
    "tag_type": 2,
    "parent_tag": 1001
  },
  "3": {
    "id": 3,
    "name": "Special attack",
    "description": "The most core and well-known signature skill move of the weapon",
    "tag_type": 1,
    "parent_tag": 1010
  },
  "4": {
    "id": 4,
    "name": "Expertise Skill",
    "description": "Skills and moves that can be freely combined and replaced with the weapon",
    "tag_type": 1,
    "parent_tag": 1010
  },
  "5": {
    "id": 5,
    "name": "Ultimate",
    "description": "The ultimate combat arcane of the most powerful weapon",
    "tag_type": 1,
    "parent_tag": 1010
  },
  "6": {
    "id": 6,
    "name": "Supplementary skill",
    "description": "Trait skill learned from talent",
    "tag_type": 1,
    "parent_tag": null
  },
  "7": {
    "id": 7,
    "name": "Recovery skill",
    "description": "Skill that can be used when being hit and airborne",
    "tag_type": 1,
    "parent_tag": null
  },
  "8": {
    "id": 8,
    "name": "Resonance skill",
    "description": "Powerful skill learned from resonance",
    "tag_type": 1,
    "parent_tag": null
  },
  "9": {
    "id": 9,
    "name": "Direct DMG",
    "description": "Damage generated by the skill move itself",
    "tag_type": 2,
    "parent_tag": 1002
  },
  "10": {
    "id": 10,
    "name": "DoT",
    "description": "Skills that affect the target or leave a DMG area that persists for a period, causing continuous DMG that cannot trigger Luck effects (this type of healing cannot trigger Luck effect)",
    "tag_type": 2,
    "parent_tag": 1002
  },
  "11": {
    "id": 11,
    "name": "Direct healing",
    "description": "Healing generated by the skill or move itself",
    "tag_type": 2,
    "parent_tag": 1003
  },
  "12": {
    "id": 12,
    "name": "HOT",
    "description": "Skills that affect the target or leave a healing area that persists for a period, causing the target to continuously restore HP (this type of healing cannot trigger Luck effects)",
    "tag_type": 2,
    "parent_tag": 1003
  },
  "13": {
    "id": 13,
    "name": "Blessing",
    "description": "In an advantageous state where combat, movement, or other abilities are enhanced",
    "tag_type": 2,
    "parent_tag": 1004
  },
  "14": {
    "id": 14,
    "name": "Exaltation",
    "description": "An effect that significantly boosts combat ability for a short period of time",
    "tag_type": 2,
    "parent_tag": 1004
  },
  "15": {
    "id": 15,
    "name": "Inspiration",
    "description": "Combat attributes are greatly enhanced, and if developed under talents, additional effects will be added",
    "tag_type": 2,
    "parent_tag": 1004
  },
  "16": {
    "id": 16,
    "name": "Weakness",
    "description": "In a disadvantageous state where combat, movement, or other abilities are reduced",
    "tag_type": 2,
    "parent_tag": 1005
  },
  "17": {
    "id": 17,
    "name": "Vulnerability",
    "description": "A detrimental effect that increases damage taken for a period of time",
    "tag_type": 2,
    "parent_tag": 1005
  },
  "18": {
    "id": 18,
    "name": "Fracture",
    "description": "Increases damage taken for a period of time, with additional effects if developed under certain talents",
    "tag_type": 2,
    "parent_tag": 1005
  },
  "19": {
    "id": 19,
    "name": "Frozen",
    "description": "In a state where movement and any combat actions are impossible",
    "tag_type": 2,
    "parent_tag": 1006
  },
  "20": {
    "id": 20,
    "name": "Bind",
    "description": "In a state where movement is impossible",
    "tag_type": 2,
    "parent_tag": 1006
  },
  "21": {
    "id": 21,
    "name": "Stun",
    "description": "In a state of immobility, unable to perform any combat actions, and unable to use items",
    "tag_type": 2,
    "parent_tag": 1006
  },
  "22": {
    "id": 22,
    "name": "Slow",
    "description": "In a state of reduced Speed",
    "tag_type": 2,
    "parent_tag": 1006
  },
  "23": {
    "id": 23,
    "name": "Stagger",
    "description": "The ability to break the super armor bar of a powerful target",
    "tag_type": 2,
    "parent_tag": 1006
  },
  "24": {
    "id": 24,
    "name": "Sprint",
    "description": "Continuous displacement type skills",
    "tag_type": 2,
    "parent_tag": 1007
  },
  "25": {
    "id": 25,
    "name": "Blink",
    "description": "Non-continuous displacement type skills",
    "tag_type": 2,
    "parent_tag": 1007
  },
  "26": {
    "id": 26,
    "name": "Shield",
    "description": "Additional health shield that absorbs damage before health",
    "tag_type": 2,
    "parent_tag": 1004
  },
  "27": {
    "id": 27,
    "name": "Block",
    "description": "A special phase of a skill where damage taken is partially mitigated",
    "tag_type": 1,
    "parent_tag": null
  },
  "28": {
    "id": 28,
    "name": "Fire",
    "description": "Skill carries the power of the Fire",
    "tag_type": 1,
    "parent_tag": null
  },
  "29": {
    "id": 29,
    "name": "Ice",
    "description": "Skill carries the power of the Ice",
    "tag_type": 1,
    "parent_tag": null
  },
  "30": {
    "id": 30,
    "name": "Thunder Element",
    "description": "Skills imbued with the power of the Thunder Element",
    "tag_type": 1,
    "parent_tag": null
  },
  "31": {
    "id": 31,
    "name": "Wind",
    "description": "Skills imbued with the power of the Wind",
    "tag_type": 1,
    "parent_tag": null
  },
  "32": {
    "id": 32,
    "name": "Rock",
    "description": "Skills imbued with the power of the Rock",
    "tag_type": 1,
    "parent_tag": null
  },
  "33": {
    "id": 33,
    "name": "Forest",
    "description": "Skills imbued with the power of the Forest",
    "tag_type": 1,
    "parent_tag": null
  },
  "34": {
    "id": 34,
    "name": "Light",
    "description": "Skills imbued with the power of the Light",
    "tag_type": 1,
    "parent_tag": null
  },
  "35": {
    "id": 35,
    "name": "Dark",
    "description": "Skills imbued with the power of the Dark",
    "tag_type": 1,
    "parent_tag": null
  },
  "36": {
    "id": 36,
    "name": "Coordination",
    "description": "Effects that synchronize attack actions with the battle",
    "tag_type": 2,
    "parent_tag": 1017
  },
  "37": {
    "id": 37,
    "name": "Cooperative Battle",
    "description": "Effects that independently perform attacks to assist in combat",
    "tag_type": 2,
    "parent_tag": 1017
  },
  "38": {
    "id": 38,
    "name": "Charging",
    "description": "A skill release method that requires some time to prepare to achieve stronger power",
    "tag_type": 1,
    "parent_tag": 1009
  },
  "39": {
    "id": 39,
    "name": "Channelling",
    "description": "A skill release method that requires maintaining a casting state to continue the effect",
    "tag_type": 1,
    "parent_tag": 1009
  },
  "40": {
    "id": 40,
    "name": "Enhancement",
    "description": "Skills in a state of being enhanced or producing changes",
    "tag_type": 1,
    "parent_tag": 1008
  },
  "41": {
    "id": 41,
    "name": "Energy Restore",
    "description": "Can obtain combat resources needed for certain skill releases",
    "tag_type": 1,
    "parent_tag": null
  },
  "42": {
    "id": 42,
    "name": "Imprint",
    "description": "A type of effect that can be triggered under specific conditions, with the trigger probability influenced by attributes",
    "tag_type": 1,
    "parent_tag": null
  },
  "43": {
    "id": 43,
    "name": "Suppress",
    "description": "A state when one's health is higher than the target's health, providing damage and Defense bonuses, and if developed under talents, additional effects will be added",
    "tag_type": 2,
    "parent_tag": 1004
  },
  "44": {
    "id": 44,
    "name": "Trap",
    "description": "A summon that produces effects after certain conditions are triggered",
    "tag_type": 2,
    "parent_tag": 1018
  },
  "45": {
    "id": 45,
    "name": "Totem",
    "description": "A summon that remains stationary for a period of time and produces effects around it",
    "tag_type": 2,
    "parent_tag": 1018
  },
  "46": {
    "id": 46,
    "name": "Companion",
    "description": "A summon that can move and follow the summoner to assist in combat",
    "tag_type": 2,
    "parent_tag": 1018
  },
  "47": {
    "id": 47,
    "name": "Construct",
    "description": "A summon with collision that can change terrain",
    "tag_type": 2,
    "parent_tag": 1018
  },
  "48": {
    "id": 48,
    "name": "Bullet",
    "description": "A small-sized, fast-moving projectile",
    "tag_type": 2,
    "parent_tag": 1019
  },
  "49": {
    "id": 49,
    "name": "Missile",
    "description": "A large-sized, moderately fast-moving projectile",
    "tag_type": 2,
    "parent_tag": 1019
  },
  "50": {
    "id": 50,
    "name": "Domain",
    "description": "Area effect that can continuously provide beneficial status to oneself or allies",
    "tag_type": 2,
    "parent_tag": 1020
  },
  "51": {
    "id": 51,
    "name": "AoE",
    "description": "Area effect that can continuously cause damage or adverse status to enemies",
    "tag_type": 2,
    "parent_tag": 1020
  },
  "52": {
    "id": 52,
    "name": "Aura",
    "description": "Can continuously provide effects to targets within its own range",
    "tag_type": 2,
    "parent_tag": 1020
  },
  "53": {
    "id": 53,
    "name": "Normal monster",
    "description": "monsters active on the continent, generally with basic combat abilities",
    "tag_type": 1,
    "parent_tag": null
  },
  "54": {
    "id": 54,
    "name": "Elite",
    "description": "Outstanding warriors among monsters, generally possessing highly threatening Expertise",
    "tag_type": 2,
    "parent_tag": 1021
  },
  "55": {
    "id": 55,
    "name": "Boss",
    "description": "The absolute strong in the group, can be called a king without exaggeration",
    "tag_type": 3,
    "parent_tag": 1022
  },
  "56": {
    "id": 56,
    "name": "Wild Boss",
    "description": "Powerful monsters found only in special territorial areas on the map",
    "tag_type": 3,
    "parent_tag": 1022
  },
  "57": {
    "id": 57,
    "name": "World Boss",
    "description": "The most powerful monster in dungeon maps",
    "tag_type": 3,
    "parent_tag": 1022
  },
  "58": {
    "id": 58,
    "name": "Healthy",
    "description": "Status where health is not less than 50% of the health cap",
    "tag_type": 1,
    "parent_tag": null
  },
  "59": {
    "id": 59,
    "name": "Injured",
    "description": "Status where health is not more than 30% of the health cap",
    "tag_type": 1,
    "parent_tag": null
  },
  "60": {
    "id": 60,
    "name": "Goblin",
    "description": "He crouched down and started digging with his hands. <br>Soon, he unearthed a box with a letter inside.",
    "tag_type": 1,
    "parent_tag": null
  },
  "61": {
    "id": 61,
    "name": "Basic Attack",
    "description": "Basic moves of the weapon",
    "tag_type": 2,
    "parent_tag": 1001
  },
  "62": {
    "id": 62,
    "name": "No element",
    "description": "Skills not imbued with elemental power",
    "tag_type": 1,
    "parent_tag": null
  },
  "63": {
    "id": 63,
    "name": "Corrosion",
    "description": "Affected by an unknown source of contamination, causing various adverse effects",
    "tag_type": 2,
    "parent_tag": 1005
  },
  "64": {
    "id": 64,
    "name": "Strong Control",
    "description": "Strong control over targets without super armor value",
    "tag_type": 1,
    "parent_tag": null
  },
  "65": {
    "id": 65,
    "name": "Counterattack",
    "description": "Attack after successful red light counter",
    "tag_type": 2,
    "parent_tag": 1001
  },
  "66": {
    "id": 66,
    "name": "Physical",
    "description": "Damage is physical, affected by Block",
    "tag_type": 1,
    "parent_tag": null
  },
  "67": {
    "id": 67,
    "name": "Magic",
    "description": "Damage is magic, not affected by Block",
    "tag_type": 1,
    "parent_tag": null
  },
  "68": {
    "id": 68,
    "name": "Single target",
    "description": "When there are fewer targets, the effect is stronger (if dealing damage, damage to the primary target does not diminish, but damage to other targets diminishes sharply)",
    "tag_type": 1,
    "parent_tag": null
  },
  "69": {
    "id": 69,
    "name": "AoE",
    "description": "Triggers a stronger effect when there are many targets (if it causes DMG, the DMG to all targets diminishes simultaneously)",
    "tag_type": 1,
    "parent_tag": null
  },
  "70": {
    "id": 70,
    "name": "Chanting",
    "description": "A skill release method that requires some time to prepare before releasing",
    "tag_type": 1,
    "parent_tag": 1009
  },
  "71": {
    "id": 71,
    "name": "Crit",
    "description": "In a state of increased Crit",
    "tag_type": 2,
    "parent_tag": 1004
  },
  "72": {
    "id": 72,
    "name": "Luck",
    "description": "In a state of increased luck",
    "tag_type": 2,
    "parent_tag": 1004
  },
  "73": {
    "id": 73,
    "name": "Acceleration",
    "description": "In a state of reduced CD",
    "tag_type": 2,
    "parent_tag": 1004
  },
  "74": {
    "id": 74,
    "name": "Mastery",
    "description": "In a state of increased mastery",
    "tag_type": 2,
    "parent_tag": 1004
  },
  "75": {
    "id": 75,
    "name": "Increased damage",
    "description": "In an advantageous state where DMG-dealing ability is enhanced",
    "tag_type": 2,
    "parent_tag": 1004
  },
  "76": {
    "id": 76,
    "name": "Protect",
    "description": "In a state of increased survivability",
    "tag_type": 2,
    "parent_tag": 1004
  },
  "77": {
    "id": 77,
    "name": "Attack Reduction",
    "description": "In a state of reduced offensive capability",
    "tag_type": 2,
    "parent_tag": 1005
  },
  "78": {
    "id": 78,
    "name": "Armor Reduce",
    "description": "In a state of reduced survivability",
    "tag_type": 2,
    "parent_tag": 1005
  },
  "79": {
    "id": 79,
    "name": "Envelop",
    "description": "In a state of immobility, unable to perform any combat actions, and continuously being knocked back and attracted",
    "tag_type": 2,
    "parent_tag": 1006
  },
  "80": {
    "id": 80,
    "name": "Crowd Control",
    "description": "Gathering enemy targets around oneself",
    "tag_type": 2,
    "parent_tag": 1006
  },
  "81": {
    "id": 81,
    "name": "Haste",
    "description": "In a state of increased haste",
    "tag_type": 2,
    "parent_tag": 1004
  },
  "82": {
    "id": 82,
    "name": "Wild Monster",
    "description": "Use to mark wild monsters, level Suppress calculation formula used",
    "tag_type": 1,
    "parent_tag": null
  },
  "83": {
    "id": 83,
    "name": "Silence",
    "description": "In a state of being unable to perform any combat actions",
    "tag_type": 2,
    "parent_tag": 1006
  },
  "84": {
    "id": 84,
    "name": "Void Corruption",
    "description": "Infected by unknown seasonal infection",
    "tag_type": 1,
    "parent_tag": null
  },
  "85": {
    "id": 85,
    "name": "Wound",
    "description": "In a state of reduced Healingiveness",
    "tag_type": 2,
    "parent_tag": 1005
  },
  "86": {
    "id": 86,
    "name": "Toy and Mount Skills",
    "description": "He crouched down and started digging with his hands. <br>Soon, he unearthed a box with a letter inside.",
    "tag_type": 1,
    "parent_tag": null
  },
  "87": {
    "id": 87,
    "name": "Transformation skill",
    "description": "Use to mark transformation buffs, use the exit button to remove all transformation buffs with this tag.",
    "tag_type": 1,
    "parent_tag": null
  },
  "88": {
    "id": 88,
    "name": "Lucky Effect DMG",
    "description": "DMG caused by Lucky Effects triggered by skills (When using class skills that deal direct DMG or healing, all Lucky Effects you possess have a chance to trigger equal to your Luck Rate)",
    "tag_type": 2,
    "parent_tag": 1002
  },
  "89": {
    "id": 89,
    "name": "Lucky Strike Healing",
    "description": "Healing caused by Lucky Effects triggered by skills (When using class skills that deal direct DMG or healing, all Lucky Effects you possess have a chance to trigger equal to your Luck Rate)",
    "tag_type": 2,
    "parent_tag": 1003
  },
  "90": {
    "id": 90,
    "name": "Main attribute",
    "description": "In a beneficial state of main attribute enhancement",
    "tag_type": 2,
    "parent_tag": 1004
  },
  "91": {
    "id": 91,
    "name": "Summon",
    "description": "A basic combat unit that repeatedly uses relatively simple skills",
    "tag_type": 2,
    "parent_tag": 1018
  },
  "92": {
    "id": 92,
    "name": "Healing Boost",
    "description": "In a state that increases Healingiveness",
    "tag_type": 2,
    "parent_tag": 1004
  },
  "93": {
    "id": 93,
    "name": "Melee",
    "description": "The skill only affects targets within close range",
    "tag_type": 1,
    "parent_tag": null
  },
  "94": {
    "id": 94,
    "name": "Ranged",
    "description": "The skill remains effective even at a longer distance from the target",
    "tag_type": 1,
    "parent_tag": null
  },
  "95": {
    "id": 95,
    "name": "Curse Stats",
    "description": "A type of buff used in roguelike gameplay",
    "tag_type": 1,
    "parent_tag": null
  },
  "96": {
    "id": 96,
    "name": "Bouncing Bullet",
    "description": "Skill marker used in roguelike gameplay",
    "tag_type": 0,
    "parent_tag": null
  },
  "140": {
    "id": 140,
    "name": "Scenario Skill",
    "description": "Additional skills obtained through scenarios or level gameplay",
    "tag_type": 1,
    "parent_tag": null
  },
  "201": {
    "id": 201,
    "name": "Field Boss",
    "description": "Quest: Participate in killing a specific type of monster",
    "tag_type": 1,
    "parent_tag": null
  },
  "202": {
    "id": 202,
    "name": "Wild",
    "description": "He crouched down and started digging with his hands. <br>Soon, he unearthed a box with a letter inside.",
    "tag_type": 1,
    "parent_tag": 1031
  },
  "203": {
    "id": 203,
    "name": "Dungeon",
    "description": "He crouched down and started digging with his hands. <br>Soon, he unearthed a box with a letter inside.",
    "tag_type": 1,
    "parent_tag": 1031
  },
  "204": {
    "id": 204,
    "name": "Melee",
    "description": "He crouched down and started digging with his hands. <br>Soon, he unearthed a box with a letter inside.",
    "tag_type": 1,
    "parent_tag": 1031
  },
  "205": {
    "id": 205,
    "name": "Ranged",
    "description": "He crouched down and started digging with his hands. <br>Soon, he unearthed a box with a letter inside.",
    "tag_type": 1,
    "parent_tag": 1031
  },
  "206": {
    "id": 206,
    "name": "Strength",
    "description": "He crouched down and started digging with his hands. <br>Soon, he unearthed a box with a letter inside.",
    "tag_type": 1,
    "parent_tag": 1031
  },
  "207": {
    "id": 207,
    "name": "Agility",
    "description": "He crouched down and started digging with his hands. <br>Soon, he unearthed a box with a letter inside.",
    "tag_type": 1,
    "parent_tag": 1031
  },
  "208": {
    "id": 208,
    "name": "Intellect",
    "description": "He crouched down and started digging with his hands. <br>Soon, he unearthed a box with a letter inside.",
    "tag_type": 1,
    "parent_tag": 1031
  },
  "209": {
    "id": 209,
    "name": "Support",
    "description": "He crouched down and started digging with his hands. <br>Soon, he unearthed a box with a letter inside.",
    "tag_type": 1,
    "parent_tag": 1031
  },
  "210": {
    "id": 210,
    "name": "Warrior",
    "description": "He crouched down and started digging with his hands. <br>Soon, he unearthed a box with a letter inside.",
    "tag_type": 1,
    "parent_tag": 1031
  },
  "211": {
    "id": 211,
    "name": "Tank",
    "description": "He crouched down and started digging with his hands. <br>Soon, he unearthed a box with a letter inside.",
    "tag_type": 1,
    "parent_tag": 1031
  },
  "212": {
    "id": 212,
    "name": "Assassin",
    "description": "He crouched down and started digging with his hands. <br>Soon, he unearthed a box with a letter inside.",
    "tag_type": 1,
    "parent_tag": 1031
  },
  "213": {
    "id": 213,
    "name": "Mage",
    "description": "He crouched down and started digging with his hands. <br>Soon, he unearthed a box with a letter inside.",
    "tag_type": 1,
    "parent_tag": 1031
  },
  "214": {
    "id": 214,
    "name": "Marksman",
    "description": "He crouched down and started digging with his hands. <br>Soon, he unearthed a box with a letter inside.",
    "tag_type": 1,
    "parent_tag": 1031
  },
  "221": {
    "id": 221,
    "name": "Minion (Dungeon)",
    "description": "He crouched down and started digging with his hands. <br>Soon, he unearthed a box with a letter inside.",
    "tag_type": 1,
    "parent_tag": 1031
  },
  "222": {
    "id": 222,
    "name": "Minor Elite (Dungeon)",
    "description": "He crouched down and started digging with his hands. <br>Soon, he unearthed a box with a letter inside.",
    "tag_type": 1,
    "parent_tag": 1031
  },
  "223": {
    "id": 223,
    "name": "Major Elite (Dungeon)",
    "description": "He crouched down and started digging with his hands. <br>Soon, he unearthed a box with a letter inside.",
    "tag_type": 1,
    "parent_tag": 1031
  },
  "224": {
    "id": 224,
    "name": "Ultra Elite (Dungeon)",
    "description": "He crouched down and started digging with his hands. <br>Soon, he unearthed a box with a letter inside.",
    "tag_type": 1,
    "parent_tag": 1031
  },
  "225": {
    "id": 225,
    "name": "Boss (Dungeon)",
    "description": "He crouched down and started digging with his hands. <br>Soon, he unearthed a box with a letter inside.",
    "tag_type": 1,
    "parent_tag": 1031
  },
  "1001": {
    "id": 1001,
    "name": "Normal Attack",
    "description": "Various moves triggered by the Basic Attack button",
    "tag_type": 1,
    "parent_tag": 1010
  },
  "1002": {
    "id": 1002,
    "name": "Damage",
    "description": "Effects that cause targets to lose HP",
    "tag_type": 1,
    "parent_tag": null
  },
  "1003": {
    "id": 1003,
    "name": "Healing",
    "description": "Effects that restore the target's HP",
    "tag_type": 1,
    "parent_tag": null
  },
  "1004": {
    "id": 1004,
    "name": "Buff",
    "description": "An effect that can be beneficial to allies in combat",
    "tag_type": 1,
    "parent_tag": null
  },
  "1005": {
    "id": 1005,
    "name": "Debuff",
    "description": "In various states that are disadvantageous to one's own combat",
    "tag_type": 1,
    "parent_tag": null
  },
  "1006": {
    "id": 1006,
    "name": "Control",
    "description": "In a state where various actions are restricted",
    "tag_type": 1,
    "parent_tag": null
  },
  "1007": {
    "id": 1007,
    "name": "Displacement",
    "description": "Skills that help characters move quickly",
    "tag_type": 1,
    "parent_tag": null
  },
  "1008": {
    "id": 1008,
    "name": "Survival",
    "description": "Skills that can help the character survive",
    "tag_type": 1,
    "parent_tag": null
  },
  "1009": {
    "id": 1009,
    "name": "Release Type",
    "description": "Special Release Method of Skill",
    "tag_type": 1,
    "parent_tag": null
  },
  "1010": {
    "id": 1010,
    "name": "Class Skills",
    "description": "Skills inherent to the Class",
    "tag_type": 1,
    "parent_tag": null
  },
  "1017": {
    "id": 1017,
    "name": "Assist in Battle",
    "description": "Auxiliary effects that can generate additional attack actions or resist offensive actions",
    "tag_type": 1,
    "parent_tag": null
  },
  "1018": {
    "id": 1018,
    "name": "Summon",
    "description": "Can summon combat units influenced by the summoner's state",
    "tag_type": 1,
    "parent_tag": null
  },
  "1019": {
    "id": 1019,
    "name": "Projectile",
    "description": "A skill mechanism that can perform physical motion and produce effects upon hitting",
    "tag_type": 1,
    "parent_tag": null
  },
  "1020": {
    "id": 1020,
    "name": "Area Effect",
    "description": "Effective method within a specified range",
    "tag_type": 1,
    "parent_tag": null
  },
  "1021": {
    "id": 1021,
    "name": "Powerful target",
    "description": "Entities far stronger than Monsters",
    "tag_type": 1,
    "parent_tag": null
  },
  "1022": {
    "id": 1022,
    "name": "Boss",
    "description": "Boss, Wild Boss, and World Boss",
    "tag_type": 2,
    "parent_tag": 1021
  },
  "1031": {
    "id": 1031,
    "name": "Monster Type Tag",
    "description": "He crouched down and started digging with his hands. <br>Soon, he unearthed a box with a letter inside.",
    "tag_type": 1,
    "parent_tag": null
  }
}
